fallingsky-0.0.8.dist-info/RECORD
fallingsky-0.0.8.dist-info/WHEEL
fallingsky-0.0.8.dist-info/metadata.json
fallingsky-0.0.8.dist-info/DESCRIPTION.rst
fallingsky-0.0.8.dist-info/METADATA
fallingsky-0.0.8.dist-info/top_level.txt
fallingsky-0.0.8.dist-info/entry_points.txt
fallingsky/walls.py
fallingsky/util.py
fallingsky/user.py
fallingsky/shapes.py
fallingsky/score.py
fallingsky/menu.py
fallingsky/main.py
fallingsky/game.py
fallingsky/block.py
fallingsky/__init__.py
fallingsky/images/background.png
fallingsky/images/banner.png
