Metadata-Version: 2.0
Name: fallingsky
Version: 0.0.8
Summary: A game of falling blocks with RPG elements, uses pygame.
Home-page: http://a-tal.github.io/fallingsky
Author: Adam Talsma
Author-email: adam@talsma.ca
License: GPLv2
Download-URL: https://github.com/a-tal/fallingsky
Platform: UNKNOWN
Classifier: Development Status :: 2 - Pre-Alpha
Classifier: Intended Audience :: End Users/Desktop
Classifier: License :: OSI Approved :: GNU General Public License v2 (GPLv2)
Classifier: Programming Language :: Python
Classifier: Programming Language :: Python :: 2.7
Classifier: Programming Language :: Python :: 3.4
Classifier: Programming Language :: Python :: Implementation :: CPython
Classifier: Topic :: Games/Entertainment
Classifier: Topic :: Games/Entertainment :: Arcade
Classifier: Topic :: Games/Entertainment :: Puzzle Games
Classifier: Topic :: Software Development :: Libraries :: pygame
Requires-Dist: kezmenu3
Requires-Dist: appdirs
